pymutator/__init__.py
pymutator/pymutator.py
pymutator/tests/__init__.py
pymutator/tests/pymutator_test.py
PyMutator-0.1.dist-info/METADATA
PyMutator-0.1.dist-info/WHEEL
PyMutator-0.1.dist-info/top_level.txt
PyMutator-0.1.dist-info/RECORD
