Metadata-Version: 2.1
Name: PyMutator
Version: 0.1
Summary: SolidJS style updating of nested python objects
Home-page: http://github.com/tompaton/pymutator
Author: Tom Paton
Author-email: tom.paton@gmail.com
License: MIT
Classifier: Programming Language :: Python :: 3
